QuickCut-0.0.1.data/data/share/applications/QuickCut.desktop
QuickCut-0.0.1.data/data/share/icons/hicolor/128x128/apps/quickcut.png
quickcut/quickcut.png
quickcut/__init__.py
quickcut/widgets.py
QuickCut-0.0.1.dist-info/entry_points.txt
QuickCut-0.0.1.dist-info/metadata.json
QuickCut-0.0.1.dist-info/DESCRIPTION.rst
QuickCut-0.0.1.dist-info/WHEEL
QuickCut-0.0.1.dist-info/top_level.txt
QuickCut-0.0.1.dist-info/RECORD
QuickCut-0.0.1.dist-info/METADATA
