Metadata-Version: 2.0
Name: QuickCut
Version: 0.0.1
Summary: Video & subtitle cut on given time-range. ffmpeg/pysrt based.
Home-page: http://github.com/eddy-geek/quickcut/
Author: Edward Oubrayrie
Author-email: edoubrayrie@gmail.com
License: GPL
Keywords: video,subtitle,editor,avi,mp4,srt,ffmpeg,pysrt
Platform: UNKNOWN
Classifier: Development Status :: 4 - Beta
Classifier: Intended Audience :: Education
Classifier: Intended Audience :: End Users/Desktop
Classifier: License :: OSI Approved :: GNU General Public License v3 or later (GPLv3+)
Classifier: Operating System :: POSIX
Classifier: Programming Language :: Python :: 3
Classifier: Programming Language :: Python :: 3.3
Classifier: Programming Language :: Python :: 3.4
Classifier: Programming Language :: Python :: 3.5
Classifier: Topic :: Multimedia :: Video
Classifier: Topic :: Utilities
Requires-Dist: pysrt
